quickcalc/__init__.py
quickcalc-0.0.1.dist-info/LICENSE
quickcalc-0.0.1.dist-info/METADATA
quickcalc-0.0.1.dist-info/WHEEL
quickcalc-0.0.1.dist-info/top_level.txt
quickcalc-0.0.1.dist-info/RECORD
