Metadata-Version: 2.1
Name: quickcalc
Version: 0.0.1
Summary: This Package will help you calculate quickly
Home-page: https://github.com/Kunal767/quickcalc
Author: Kunal Gupta A.K.A Macstock Tech
Author-email: kunalgupta8122@gmail.com
License: UNKNOWN
Project-URL: Bug Tracker, https://github.com/Kunal767/quickcalc/issues
Platform: UNKNOWN
Classifier: Programming Language :: Python :: 3
Classifier: License :: OSI Approved :: MIT License
Classifier: Operating System :: OS Independent
Requires-Python: >=3.6
License-File: LICENSE
